jaxloop/__init__.py
jaxloop/actions.py
jaxloop-0.0.1.dist-info/WHEEL
jaxloop-0.0.1.dist-info/METADATA
jaxloop-0.0.1.dist-info/RECORD
