Metadata-Version: 2.1
Name: jaxloop
Version: 0.0.1
Summary: A loop library.
Author-email: Jeff Carpenter <code@jeffcarp.com>
Requires-Python: >=3.8
Classifier: Programming Language :: Python :: 3
Classifier: License :: OSI Approved :: MIT License
Classifier: Operating System :: OS Independent
Project-URL: Homepage, https://github.com/jeffcarp/loop-docs
Project-URL: Issues, https://github.com/jeffcarp/loop-docs/issues
